<?xml version="1.0" encoding="utf-8"?>
<!--
	EGHV : Enhanced Goodies and Hostile Villagers for Civilization VI
	Copyright (C) 2020-2021 zzragnar0kzz
	All rights reserved
-->
<!-- localized in-game text for es_ES -->
<GameData>
	<LocalizedText>
        <!-- in-game hostile villager notifications -->
        <Replace Tag="LOC_HOSTILE_VILLAGERS_NOTIFICATION_TITLE" Language="es_ES">
            <Text>Aldeanos Hostiles</Text>
        </Replace>
        <Replace Tag="LOC_HOSTILE_VILLAGERS_UNIT_NOTIFICATION_MESSAGE" Language="es_ES">
            <Text>¡Algunos de los aldeanos están enojados porque su tribu trató con forasteros, y se han organizado en una unidad cuerpo a cuerpo hostil en represalia!</Text>
        </Replace>
        <Replace Tag="LOC_HOSTILE_VILLAGERS_CAMP_NOTIFICATION_MESSAGE" Language="es_ES">
            <Text>¡Los aldeanos son extremadamente hostiles a la presencia de forasteros y han creado un nuevo campamento desde el que lanzar más ataques!</Text>
        </Replace>
        <!-- new goody hut reward descriptions : hostiles-type -->
        <Replace Tag="LOC_GOODYHUT_SPAWN_HOSTILE_VILLAGERS_DESCRIPTION" Language="es_ES">
            <Text>[COLOR_RED]¡Aparecen aldeanos hostiles![ENDCOLOR]</Text>
        </Replace>
        <!-- replacement goody hut reward description : culture-type : free relic (now faith-type) -->
        <Replace Tag="LOC_GOODYHUT_CULTURE_RELIC_DESCRIPTION" Language="es_ES">
			<Text>Se otorgó una [ICON_GreatWork_Relic] reliquia</Text>
		</Replace>
        <!-- new goody hut reward descriptions : culture-type -->
        <Replace Tag="LOC_GOODYHUT_CULTURE_ONE_CIVIC_DESCRIPTION" Language="es_ES">
            <Text>[COLOR_FLOAT_CULTURE]Un Cívico gratis[ENDCOLOR]</Text>
        </Replace>
        <Replace Tag="LOC_GOODYHUT_CULTURE_TWO_CIVICS_DESCRIPTION" Language="es_ES">
            <Text>[COLOR_FLOAT_CULTURE]Dos Cívicos gratis[ENDCOLOR]</Text>
        </Replace>
        <Replace Tag="LOC_GOODYHUT_CULTURE_SMALL_CHANGE_DESCRIPTION" Language="es_ES">
            <Text>[COLOR_FLOAT_CULTURE]+{1_Num} [ICON_CultureLarge] Cultura en todas las ciudades[ENDCOLOR]</Text>
        </Replace>
        <Replace Tag="LOC_GOODYHUT_CULTURE_SMALL_MODIFIER_DESCRIPTION" Language="es_ES">
            <Text>[COLOR_FLOAT_CULTURE]+{1_Num}% [ICON_CultureLarge] Cultura en todas las ciudades[ENDCOLOR]</Text>
        </Replace>
        <!-- new goody hut reward descriptions : faith-type -->
        <Replace Tag="LOC_GOODYHUT_FAITH_SMALL_CHANGE_DESCRIPTION" Language="es_ES">
            <Text>+{1_Num} [ICON_FaithLarge] Fe en todas las ciudades</Text>
        </Replace>
        <Replace Tag="LOC_GOODYHUT_FAITH_SMALL_MODIFIER_DESCRIPTION" Language="es_ES">
            <Text>+{1_Num}% [ICON_FaithLarge] Fe en todas las ciudades</Text>
        </Replace>
        <!-- new goody hut reward descriptions : gold-type -->
        <Replace Tag="LOC_GOODYHUT_ADD_TRADE_ROUTE_DESCRIPTION" Language="es_ES">
            <Text>[COLOR_FLOAT_GOLD]+{1_Num} [ICON_TradeRouteLarge] ruta comercial(es)[ENDCOLOR]</Text>
        </Replace>
        <Replace Tag="LOC_GOODYHUT_GOLD_SMALL_CHANGE_DESCRIPTION" Language="es_ES">
            <Text>[COLOR_FLOAT_GOLD]+{1_Num} [ICON_GoldLarge] Oro en todas las ciudades[ENDCOLOR]</Text>
        </Replace>
        <Replace Tag="LOC_GOODYHUT_GOLD_SMALL_MODIFIER_DESCRIPTION" Language="es_ES">
            <Text>[COLOR_FLOAT_GOLD]+{1_Num}% [ICON_GoldLarge] Oro en todas las ciudades[ENDCOLOR]</Text>
        </Replace>
        <!-- replacement goody hut reward description : military-type : grant recon unit -->
        <Replace Tag="LOC_GOODYHUT_MILITARY_GRANT_UNIT_DESCRIPTION" Language="es_ES">
			<Text>[COLOR_FLOAT_MILITARY]Los aldeanos te proporcionan un Explorador[ENDCOLOR]</Text>
		</Replace>
        <!-- new goody hut reward descriptions : military-type -->
        <Replace Tag="LOC_GOODYHUT_MILITARY_GRANT_MELEE_UNIT_DESCRIPTION" Language="es_ES">
            <Text>[COLOR_FLOAT_MILITARY]Los aldeanos te proporcionan un Guerrero[ENDCOLOR]</Text>
        </Replace>
        <Replace Tag="LOC_GOODYHUT_MILITARY_GRANT_RANGED_UNIT_DESCRIPTION" Language="es_ES">
            <Text>[COLOR_FLOAT_MILITARY]Los aldeanos te proporcionan un Honda[ENDCOLOR]</Text>
        </Replace>
        <Replace Tag="LOC_GOODYHUT_MILITARY_GRANT_ANTI_CAVALRY_UNIT_DESCRIPTION" Language="es_ES">
            <Text>[COLOR_FLOAT_MILITARY]Los aldeanos te proporcionan un Lancero[ENDCOLOR]</Text>
        </Replace>
        <Replace Tag="LOC_GOODYHUT_MILITARY_GRANT_LIGHT_CAVALRY_UNIT_DESCRIPTION" Language="es_ES">
            <Text>[COLOR_FLOAT_MILITARY]Los aldeanos te proporcionan un Jinete[ENDCOLOR]</Text>
        </Replace>
        <Replace Tag="LOC_GOODYHUT_MILITARY_GRANT_HEAVY_CAVALRY_UNIT_DESCRIPTION" Language="es_ES">
            <Text>[COLOR_FLOAT_MILITARY]Los aldeanos te proporcionan un Carro Pesado[ENDCOLOR]</Text>
        </Replace>
        <Replace Tag="LOC_GOODYHUT_MILITARY_GRANT_MILITARY_ENGINEER_DESCRIPTION" Language="es_ES">
            <Text>[COLOR_FLOAT_MILITARY]Los aldeanos te proporcionan un Ingeniero Militar[ENDCOLOR]</Text>
        </Replace>
        <Replace Tag="LOC_GOODYHUT_MILITARY_GRANT_MEDIC_DESCRIPTION" Language="es_ES">
            <Text>[COLOR_FLOAT_MILITARY]Los aldeanos te proporcionan un Médico[ENDCOLOR]</Text>
        </Replace>
        <Replace Tag="LOC_GOODYHUT_PRODUCTION_SMALL_CHANGE_DESCRIPTION" Language="es_ES">
            <Text>[COLOR_FLOAT_MILITARY]+{1_Num} a toda la [ICON_ProductionLarge] Producción en todas las ciudades[ENDCOLOR]</Text>
        </Replace>
        <Replace Tag="LOC_GOODYHUT_PRODUCTION_SMALL_MODIFIER_DESCRIPTION" Language="es_ES">
            <Text>[COLOR_FLOAT_MILITARY]+{1_Num}% a toda la [ICON_ProductionLarge] Producción en todas las ciudades[ENDCOLOR]</Text>
        </Replace>
        <!-- new goody hut reward descriptions : science-type -->
        <Replace Tag="LOC_GOODYHUT_SCIENCE_TWO_TECHS_DESCRIPTION" Language="es_ES">
            <Text>[COLOR_FLOAT_SCIENCE]Dos Tecnologías gratis[ENDCOLOR]</Text>
        </Replace>
        <Replace Tag="LOC_GOODYHUT_SCIENCE_SMALL_CHANGE_DESCRIPTION" Language="es_ES">
            <Text>[COLOR_FLOAT_SCIENCE]+{1_Num} [ICON_ScienceLarge] Ciencia en todas las ciudades[ENDCOLOR]</Text>
        </Replace>
        <Replace Tag="LOC_GOODYHUT_SCIENCE_SMALL_MODIFIER_DESCRIPTION" Language="es_ES">
            <Text>[COLOR_FLOAT_SCIENCE]+{1_Num}% [ICON_ScienceLarge] Ciencia en todas las ciudades[ENDCOLOR]</Text>
        </Replace>
        <!-- replacement goody hut reward description : survivors-type : add population -->
        <Replace Tag="LOC_GOODYHUT_SURVIVORS_ADD_POP_DESCRIPTION" Language="es_ES">
			<Text>+{1_Num} [ICON_Citizen] población</Text>
		</Replace>
        <!-- replacement goody hut reward description : survivors-type : grant civilian unit -->
		<Replace Tag="LOC_GOODYHUT_SURVIVORS_GRANT_UNIT_DESCRIPTION" Language="es_ES">
			<Text>Se le concede {1_Num}  {1_Num: plural 1?{2_Unit} unidad; other?{2_Unit} unidades;}</Text>
		</Replace>
        <!-- new goody hut reward descriptions : survivors-type -->
        <Replace Tag="LOC_GOODYHUT_FOOD_SMALL_CHANGE_DESCRIPTION" Language="es_ES">
            <Text>+{1_Num} [ICON_FoodLarge] Comida en todas las ciudades</Text>
        </Replace>
        <Replace Tag="LOC_GOODYHUT_FOOD_SMALL_MODIFIER_DESCRIPTION" Language="es_ES">
            <Text>+{1_Num}% [ICON_FoodLarge] Comida en todas las ciudades</Text>
        </Replace>
    </LocalizedText>
</GameData>
